[
  {
    "id": 2,
    "nome": "Caramelo",
    "raca": "Vira - Lata",
    "genero": "Macho",
    "idade": "1 ano",
    "descricao": "Visto pela última vez próximo ao senac na avenida vicente simões.",
    "imagem": "/uploads/caramelo02.jpg",
    "status": "perdido"
  },
  {
    "id": 3,
    "nome": "Spike",
    "raca": "golden",
    "genero": "Macho",
    "idade": "2 anos",
    "descricao": "Esta com uma coleira azul.",
    "imagem": "/uploads/pet05.jpg",
    "status": "perdido"
  },
  {
    "id": 7,
    "nome": "Bolota",
    "raca": "Pug",
    "genero": "Fêmea",
    "idade": "1 ano e 6 meses",
    "descricao": "Desapareceu no bairro Jardim Paraíso. Atende pelo nome Bolota.",
    "imagem": "/uploads/bolotapug.jpg",
    "status": "perdido"
  },
  {
    "id": 9,
    "nome": "Nina",
    "raca": "Sem raça definida",
    "genero": "Fêmea",
    "idade": "7 meses",
    "descricao": "Filhote sociável e brincalhona. Perdeu-se na região do centro.",
    "imagem": "/uploads/ninapet.jpg",
    "status": "perdido"
  }
]
